{
  "opendb_id": "cf8b6311-a306-4b97-9404-dbf2a1e6981a",
  "power_connectors": {
    "pcie_6_pin": 0,
    "pcie_8_pin": 0,
    "pcie_12VHPWR": 0,
    "pcie_12V_2x6": 0
  },
  "metadata": {
    "name": "Gigabyte AERO OC GeForce RTX 5060 8GB GDDR7 Silver",
    "manufacturer": "Gigabyte",
    "part_numbers": [
      "GV-N5060AERO OC-8GD"
    ],
    "series": "GeForce RTX 5060",
    "variant": "Gigabyte"
  },
  "chipset_manufacturer": "GeForce",
  "chipset": "GeForce RTX 5060",
  "memory": 8,
  "memory_type": "GDDR7",
  "core_base_clock": 2280,
  "core_boost_clock": 2280,
  "effective_memory_clock": 28000,
  "memory_bus": 128,
  "interface": "PCIe x16",
  "color": [
    "GREY"
  ],
  "length": 281,
  "tdp": 145,
  "total_slot_width": 2,
  "cooling": "3 Fans",
  "video_outputs": {
    "hdmi_2_1": 1,
    "hdmi_2_0": 0,
    "displayport_2_1": 3,
    "displayport_2_1a": 0,
    "displayport_1_4a": 0,
    "dvi_d": 0,
    "vga": 0,
    "_id": "685215c40c9749f19a4efa99"
  },
  "core_count": 3840,
  "general_product_information": {
    "amazon_sku": "B0F8MH9LG2",
    "newegg_sku": "N82E16814932799",
    "bestbuy_sku": 6632707,
    "walmart_sku": 16933250096
  }
}